{
  "date": "2026-04-07",
  "category": "property",
  "article_count": 200,
  "source_count": 4,
  "matched_count": 182,
  "top_entities": [
    {
      "name": "PropertyGeneral",
      "count": 284
    },
    {
      "name": "Market",
      "count": 162
    },
    {
      "name": "PropertyType",
      "count": 156
    },
    {
      "name": "Location",
      "count": 67
    },
    {
      "name": "Policy",
      "count": 58
    },
    {
      "name": "Developer",
      "count": 33
    }
  ],
  "sources": {
    "매일경제 부동산": 74,
    "한경 부동산": 67,
    "PropertyWire UK": 8,
    "Realtor.com News": 51
  },
  "generated_at": "2026-04-07T16:07:43.937555+09:00"
}